{
  "project_info": {
    "project_number": "376115546326",
    "project_id": "voicecontrol-fe913",
    "storage_bucket": "voicecontrol-fe913.appspot.com"
  },
  "client": [
    {
      "client_info": {
        "mobilesdk_app_id": "1:376115546326:android:927812ff930a8519dd2177",
        "android_client_info": {
          "package_name": "com.radenmas.voice_control"
        }
      },
      "oauth_client": [
        {
          "client_id": "376115546326-u877p0vpj6558mp6o5gbfkvc50qopbis.apps.googleusercontent.com",
          "client_type": 1,
          "android_info": {
            "package_name": "com.radenmas.voice_control",
            "certificate_hash": "d16a9e947e12ce07f0faf576488044772f6c3b7a"
          }
        },
        {
          "client_id": "376115546326-sivhcul3re3msvmfnkgi809ngikv0ndl.apps.googleusercontent.com",
          "client_type": 3
        }
      ],
      "api_key": [
        {
          "current_key": "AIzaSyAIgseCc0jZsLFPoUFXORUr2ve0os68ALs"
        }
      ],
      "services": {
        "appinvite_service": {
          "other_platform_oauth_client": [
            {
              "client_id": "376115546326-sivhcul3re3msvmfnkgi809ngikv0ndl.apps.googleusercontent.com",
              "client_type": 3
            }
          ]
        }
      }
    }
  ],
  "configuration_version": "1"
}